shialifube/__init__.py
shialifube/transliterator.py
shialifube-0.1.2.dist-info/METADATA
shialifube-0.1.2.dist-info/WHEEL
shialifube-0.1.2.dist-info/top_level.txt
shialifube-0.1.2.dist-info/RECORD
