Metadata-Version: 2.1
Name: shialifube
Version: 0.1.2
Summary: Transliteration of Comorian into Arabic Script
Home-page: https://github.com/nairaxo
Author: Abdou Mohamed Naira
Author-email: naira.abdoumohamed@gmail.com
Classifier: Programming Language :: Python :: 3
Classifier: License :: OSI Approved :: MIT License
Classifier: Operating System :: OS Independent
Requires-Python: >=3.6
